Metadata-Version: 2.1
Name: indic-translit
Version: 0.1.3.1
Summary: Transliterate to and from Indian languages. Currently supported Dravida languages - ಕతెമத.
Home-page: https://github.com/Posterior-AI/dravida-transliterate
Author: posteriorai
Author-email: jaswanth@posterior.xyz
License-File: LICENSE
